turbogpt/__init__.py
turbogpt/turbogpt.py
turbogpt-1.0.1.dist-info/LICENSE.TXT
turbogpt-1.0.1.dist-info/METADATA
turbogpt-1.0.1.dist-info/WHEEL
turbogpt-1.0.1.dist-info/top_level.txt
turbogpt-1.0.1.dist-info/RECORD
