Metadata-Version: 2.1
Name: turbogpt
Version: 1.0.1
Summary: A python based wrapper for GPT-4 & GPT-3.5 PLUS.
Author: daan-dj
Author-email: daan@jumelet.net
Classifier: Programming Language :: Python :: 3
Classifier: License :: OSI Approved :: MIT License
Classifier: Operating System :: OS Independent
Requires-Python: >=3.6
License-File: LICENSE.TXT
Requires-Dist: python-dotenv (==1.0.0)
Requires-Dist: tls-client (==0.1.9)
